buildml/__init__.py
buildml/_automate.py
buildml/automate.py
buildml/date.py
buildml/eda.py
buildml/model.py
buildml/output_dataset.py
buildml/preprocessing.py
buildml/automate/__init__.py
buildml/automate/_automate.py
buildml/build_model/__init__.py
buildml/build_model/_model.py
buildml/date_features/__init__.py
buildml/date_features/_date.py
buildml/eda/__init__.py
buildml/eda/_eda.py
buildml/output_dataset/__init__.py
buildml/output_dataset/_output_dataset.py
buildml/preprocessing/__init__.py
buildml/preprocessing/_preprocessing.py
buildml-1.0.9.dist-info/LICENSE
buildml-1.0.9.dist-info/METADATA
buildml-1.0.9.dist-info/WHEEL
buildml-1.0.9.dist-info/top_level.txt
buildml-1.0.9.dist-info/RECORD
