Metadata-Version: 2.1
Name: buildml
Version: 1.0.9
Summary: Let's make building machine learning models the complex way, easy.
Author: TechLeo (Onyiriuba Leonard Chukwubuikem)
Author-email: <techleo.ng@outlook.com>
License: MIT
Keywords: machine learning,data science,data preprocessing,supervised learning,data exploration,ML framework,data cleaning,regression,classification,machine learning toolkit
Classifier: Development Status :: 4 - Beta
Classifier: Intended Audience :: End Users/Desktop
Classifier: Intended Audience :: Developers
Classifier: Intended Audience :: Science/Research
Classifier: License :: OSI Approved :: MIT License
Classifier: Programming Language :: Python :: 3
Classifier: Programming Language :: Python :: 3.6
Classifier: Programming Language :: Python :: 3.7
Classifier: Programming Language :: Python :: 3.8
Classifier: Programming Language :: Python :: 3.9
Classifier: Operating System :: Unix
Classifier: Operating System :: MacOS :: MacOS X
Classifier: Operating System :: Microsoft :: Windows
Requires-Python: >=3.0
License-File: LICENSE
Requires-Dist: datatable
Requires-Dist: imbalanced-learn
Requires-Dist: imblearn
Requires-Dist: matplotlib
Requires-Dist: numpy
Requires-Dist: pandas
Requires-Dist: scikit-learn
Requires-Dist: seaborn
Requires-Dist: setuptools
Requires-Dist: sweetviz
Requires-Dist: ydata-profiling
